otpwd/Otpwd.py
otpwd/__init__.py
Otpwd-0.0.6.dist-info/LICENSE
Otpwd-0.0.6.dist-info/METADATA
Otpwd-0.0.6.dist-info/WHEEL
Otpwd-0.0.6.dist-info/top_level.txt
Otpwd-0.0.6.dist-info/RECORD
