Metadata-Version: 2.1
Name: Otpwd
Version: 0.0.6
Summary: Dynamic encryption software program
Home-page: UNKNOWN
Author: v-k
Author-email: vvvkkk1960@outlook.com
License: UNKNOWN
Platform: UNKNOWN
Classifier: Programming Language :: Python :: 3.8
